mkdpdf/__init__.py
mkdpdf/configuration.py
mkdpdf/utilities.py
mkdpdf/document/__init__.py
mkdpdf/document/document.py
mkdpdf/document/templates/pdf/style/document.css
mkdpdf/document/templates/pdf/style/footer.css
mkdpdf/document/templates/pdf/style/header.css
mkdpdf/document/templates/pdf/style/mermaid.css
mkdpdf/document/templates/pdf/style/pdf.css
mkdpdf/document/templates/pdf/style/reset.css
mkdpdf/documentation/__init__.py
mkdpdf/documentation/documentation.py
mkdpdf/documentation/templates/md/header.md
mkdpdf/documentation/templates/md/main.md
mkdpdf/documentation/templates/md/class/header.md
mkdpdf/documentation/templates/md/class/main.md
mkdpdf/documentation/templates/md/functions/header.md
mkdpdf/documentation/templates/md/functions/main.md
mkdpdf/documentation/templates/pdf/style/document.css
mkdpdf/documentation/templates/pdf/style/footer.css
mkdpdf/documentation/templates/pdf/style/header.css
mkdpdf/md/__init__.py
mkdpdf/md/md.py
mkdpdf/pdf/__init__.py
mkdpdf/pdf/pdf.py
mkdpdf/pdf/publisher.py
mkdpdf/report/__init__.py
mkdpdf/report/report.py
mkdpdf/report/templates/md/footer.md
mkdpdf/report/templates/md/header.md
mkdpdf/report/templates/md/main.md
mkdpdf/report/templates/pdf/footer.html
mkdpdf/report/templates/pdf/header.html
mkdpdf/report/templates/pdf/main.html
mkdpdf/report/templates/pdf/style/document.css
mkdpdf/report/templates/pdf/style/footer.css
mkdpdf/report/templates/pdf/style/header.css
mkdpdf/report/templates/pdf/style/pdf.css
mkdpdf-0.2.7.dist-info/METADATA
mkdpdf-0.2.7.dist-info/WHEEL
mkdpdf-0.2.7.dist-info/entry_points.txt
mkdpdf-0.2.7.dist-info/top_level.txt
mkdpdf-0.2.7.dist-info/RECORD
