Metadata-Version: 2.1
Name: mkdpdf
Version: 0.2.7
Summary: Python package render engine for Markdown (Markdown) and PDF (Weasyprint).
Home-page: https://gitlab.com/lgensinger/mkdpdf
Requires-Dist: markdown
Requires-Dist: pyyaml
Requires-Dist: weasyprint (==52.5)
Provides-Extra: test
Requires-Dist: pkgparser ; extra == 'test'
Requires-Dist: pytest ; extra == 'test'
Requires-Dist: pytest-cov ; extra == 'test'
